depqdict/__init__.py
depqdict/depqdict.py
depqdict/py.typed
depqdict-0.1.1.dist-info/METADATA
depqdict-0.1.1.dist-info/WHEEL
depqdict-0.1.1.dist-info/licenses/LICENSE
depqdict-0.1.1.dist-info/RECORD
